i3_battery_block_vgg/__init__.py
i3_battery_block_vgg/__main__.py
i3_battery_block_vgg/battery.py
i3_battery_block_vgg/battery_timer.py
i3_battery_block_vgg/cli.py
i3_battery_block_vgg/font_awesome_glyphs.py
i3_battery_block_vgg/html_formatter.py
i3_battery_block_vgg/state.py
i3_battery_block_vgg/timeparser.py
i3_battery_block_vgg-0.4.0.dist-info/AUTHORS.rst
i3_battery_block_vgg-0.4.0.dist-info/LICENSE
i3_battery_block_vgg-0.4.0.dist-info/METADATA
i3_battery_block_vgg-0.4.0.dist-info/WHEEL
i3_battery_block_vgg-0.4.0.dist-info/entry_points.txt
i3_battery_block_vgg-0.4.0.dist-info/top_level.txt
i3_battery_block_vgg-0.4.0.dist-info/RECORD
