Metadata-Version: 2.1
Name: i3-battery-block-vgg
Version: 0.4.0
Summary: An i3 wm block for showing the battery state. Based on battery2 from James Murphy. https://github.com/vivien/i3blocks-contrib]
Home-page: https://github.com/vgoehler/python-i3-battery-block
Author: Volker G Göhler
Author-email: volker.goehler@informatik.tu-freiberg.de
License: BSD-2-Clause
Project-URL: Documentation, https://python-i3-battery-block.readthedocs.io/
Project-URL: Changelog, https://python-i3-battery-block.readthedocs.io/en/latest/changelog.html
Project-URL: Issue Tracker, https://github.com/vgoehler/python-i3-battery-block/issues
Platform: UNKNOWN
Classifier: Development Status :: 5 - Production/Stable
Classifier: Intended Audience :: Developers
Classifier: License :: OSI Approved :: BSD License
Classifier: Operating System :: Unix
Classifier: Operating System :: POSIX
Classifier: Operating System :: Microsoft :: Windows
Classifier: Programming Language :: Python
Classifier: Programming Language :: Python :: 3
Classifier: Programming Language :: Python :: 3.6
Classifier: Programming Language :: Python :: 3.7
Classifier: Programming Language :: Python :: 3.8
Classifier: Topic :: Utilities
Requires-Python: >=3.6
